aoikbookmarkstofiles/aoikbtf.py
aoikbookmarkstofiles/__init__.py
aoikbookmarkstofiles/__main__.py
aoikbookmarkstofiles/i18n/cn.yml
aoikbookmarkstofiles/i18n/cp936.yml
aoikbookmarkstofiles/i18n/en.yml
aoikbookmarkstofiles/i18n/en_us.yml
aoikbookmarkstofiles/i18n/gbk.yml
aoikbookmarkstofiles/i18n/hz.yml
aoikbookmarkstofiles/i18n/ja.yml
aoikbookmarkstofiles/i18n/ja_JP.yml
aoikbookmarkstofiles/i18n/jp.yml
aoikbookmarkstofiles/i18n/zh.yml
aoikbookmarkstofiles/i18n/zh_cn.yml
aoikbookmarkstofiles/i18n/__init__.py
AoikBookmarksToFiles-0.1.5.dist-info/DESCRIPTION.rst
AoikBookmarksToFiles-0.1.5.dist-info/entry_points.txt
AoikBookmarksToFiles-0.1.5.dist-info/METADATA
AoikBookmarksToFiles-0.1.5.dist-info/metadata.json
AoikBookmarksToFiles-0.1.5.dist-info/RECORD
AoikBookmarksToFiles-0.1.5.dist-info/top_level.txt
AoikBookmarksToFiles-0.1.5.dist-info/WHEEL
