Metadata-Version: 2.0
Name: AoikBookmarksToFiles
Version: 0.1.5
Summary: Convert a bookmark file in NETSCAPE-Bookmark-file-1 format exported from browsers like Chrome and Firefox into a set of Windows ".url" files or Gnome ".desktop" files.
Home-page: https://github.com/AoiKuiyuyou/AoikBookmarksToFiles
Author: Aoi.Kuiyuyou
Author-email: aoi.kuiyuyou@google.com
License: MIT
Keywords: convert browser bookmark file Windows url file Gnome desktop file
Platform: UNKNOWN
Classifier: Development Status :: 3 - Alpha
Classifier: Environment :: Console
Classifier: Intended Audience :: End Users/Desktop
Classifier: License :: OSI Approved :: MIT License
Classifier: Operating System :: Microsoft :: Windows
Classifier: Operating System :: POSIX :: Linux
Classifier: Programming Language :: Python :: 2
Classifier: Programming Language :: Python :: 2.7
Classifier: Programming Language :: Python :: 3
Classifier: Programming Language :: Python :: 3.3
Classifier: Programming Language :: Python :: 3.4
Requires-Dist: pyyaml
Requires-Dist: AoikSixyIO
Requires-Dist: AoikI18n
